{
  "animateLoading": true,
  "borderOpacity": 100,
  "borderRadius": "{{appsmith.theme.borderRadius.appBorderRadius}}",
  "borderWidth": 1,
  "bottomRow": 84,
  "boxShadow": "{{appsmith.theme.boxShadow.appBoxShadow}}",
  "dynamicBindingPathList": [
    {
      "key": "borderRadius"
    },
    {
      "key": "boxShadow"
    }
  ],
  "flexVerticalAlignment": "start",
  "isLoading": false,
  "isVisible": true,
  "key": "blc2jkzgtc",
  "leftColumn": 0,
  "mobileBottomRow": 62,
  "mobileLeftColumn": 0,
  "mobileRightColumn": 12,
  "mobileTopRow": 30,
  "needsErrorInfo": false,
  "parentColumnSpace": 19.90625,
  "parentId": "esfh9fxray",
  "parentRowSpace": 10,
  "renderMode": "CANVAS",
  "responsiveBehavior": "fill",
  "rightColumn": 64,
  "source": "https://www.example.com",
  "topRow": 30,
  "type": "IFRAME_WIDGET",
  "version": 1,
  "widgetId": "id7apnoe78",
  "widgetName": "Iframe2"
}