{
  "gitSyncId": "66f263e90ea81e705fc1052a_d706ad56-bae9-49dd-b31f-a9fcdb4a6820",
  "id": "Screeny_inventory_i18n.setup",
  "pluginId": "js-plugin",
  "pluginType": "JS",
  "unpublishedAction": {
    "actionConfiguration": {
      "encodeParamsToggle": true,
      "jsArguments": [
        {
          "name": "lang",
          "value": "english"
        }
      ],
      "paginationType": "NONE",
      "timeoutInMillisecond": 10000
    },
    "collectionId": "Screeny_inventory_i18n",
    "confirmBeforeExecute": false,
    "datasource": {
      "isAutoGenerated": false,
      "name": "UNUSED_DATASOURCE",
      "pluginId": "js-plugin"
    },
    "dynamicBindingPathList": [
      {
        "key": "body"
      }
    ],
    "executeOnLoad": true,
    "fullyQualifiedName": "i18n.setup",
    "name": "setup",
    "pageId": "Screeny_inventory",
    "userSetOnLoad": true
  }
}