{
  "accentColor": "{{appsmith.theme.colors.primaryColor}}",
  "animateLoading": true,
  "autoFocus": false,
  "borderRadius": "{{appsmith.theme.borderRadius.appBorderRadius}}",
  "bottomRow": 15,
  "boxShadow": "none",
  "defaultText": "{{doplatakolorzapytaj.data[0].doplata||0}}",
  "dynamicBindingPathList": [
    {
      "key": "accentColor"
    },
    {
      "key": "borderRadius"
    },
    {
      "key": "defaultText"
    }
  ],
  "dynamicHeight": "FIXED",
  "dynamicTriggerPathList": [],
  "iconAlign": "left",
  "inputType": "TEXT",
  "isDisabled": false,
  "isLoading": false,
  "isRequired": false,
  "isVisible": true,
  "key": "kzo0p2nyk7",
  "label": "Label",
  "labelAlignment": "left",
  "labelPosition": "Top",
  "labelStyle": "",
  "labelTextSize": "0.875rem",
  "labelWidth": 5,
  "leftColumn": 0,
  "maxDynamicHeight": 9000,
  "minDynamicHeight": 4,
  "minWidth": 450,
  "mobileBottomRow": 15,
  "mobileLeftColumn": 0,
  "mobileRightColumn": 11,
  "mobileTopRow": 8,
  "needsErrorInfo": false,
  "parentColumnSpace": 18.65625,
  "parentId": "ikmrmo799q",
  "parentRowSpace": 10,
  "renderMode": "CANVAS",
  "resetOnSubmit": true,
  "responsiveBehavior": "fill",
  "rightColumn": 11,
  "shouldAllowAutofill": false,
  "showStepArrows": false,
  "topRow": 8,
  "type": "INPUT_WIDGET_V2",
  "version": 2,
  "widgetId": "2l9q2uap3t",
  "widgetName": "doplatakolorinput"
}