{
  "gitSyncId": "670a2c74cb4eb2140bfd1e60_ca0fda65-0013-41b8-b518-6416ff6c24cd",
  "id": "Podsumowanie_pdf_polski_z_rabatami_pobierz.nazwapliku",
  "pluginId": "js-plugin",
  "pluginType": "JS",
  "unpublishedAction": {
    "actionConfiguration": {
      "encodeParamsToggle": true,
      "jsArguments": [],
      "paginationType": "NONE",
      "timeoutInMillisecond": 10000
    },
    "collectionId": "Podsumowanie_pdf_polski_z_rabatami_pobierz",
    "confirmBeforeExecute": false,
    "datasource": {
      "isAutoGenerated": false,
      "name": "UNUSED_DATASOURCE",
      "pluginId": "js-plugin"
    },
    "dynamicBindingPathList": [
      {
        "key": "body"
      }
    ],
    "executeOnLoad": true,
    "fullyQualifiedName": "pdf_polski_z_rabatami_pobierz.nazwapliku",
    "name": "nazwapliku",
    "pageId": "Podsumowanie",
    "userSetOnLoad": true
  }
}